huaweicloudsdkcore/__init__.py
huaweicloudsdkcore/client.py
huaweicloudsdkcore/sdk_request.py
huaweicloudsdkcore/sdk_response.py
huaweicloudsdkcore/sdk_stream_request.py
huaweicloudsdkcore/sdk_stream_response.py
huaweicloudsdkcore/auth/__init__.py
huaweicloudsdkcore/auth/credentials.py
huaweicloudsdkcore/auth/endpoint.py
huaweicloudsdkcore/auth/internal.py
huaweicloudsdkcore/auth/provider.py
huaweicloudsdkcore/exceptions/__init__.py
huaweicloudsdkcore/exceptions/exception_handler.py
huaweicloudsdkcore/exceptions/exceptions.py
huaweicloudsdkcore/exchange/__init__.py
huaweicloudsdkcore/exchange/api_reference.py
huaweicloudsdkcore/exchange/exchange.py
huaweicloudsdkcore/http/__init__.py
huaweicloudsdkcore/http/bson_types.py
huaweicloudsdkcore/http/formdata.py
huaweicloudsdkcore/http/future_session.py
huaweicloudsdkcore/http/http_client.py
huaweicloudsdkcore/http/http_config.py
huaweicloudsdkcore/http/http_handler.py
huaweicloudsdkcore/http/primitive_types.py
huaweicloudsdkcore/http/progress.py
huaweicloudsdkcore/http/user_agent.py
huaweicloudsdkcore/invoker/__init__.py
huaweicloudsdkcore/invoker/invoker.py
huaweicloudsdkcore/region/__init__.py
huaweicloudsdkcore/region/cache.py
huaweicloudsdkcore/region/provider.py
huaweicloudsdkcore/region/region.py
huaweicloudsdkcore/retry/__init__.py
huaweicloudsdkcore/retry/backoff_strategy.py
huaweicloudsdkcore/signer/__init__.py
huaweicloudsdkcore/signer/algorithm.py
huaweicloudsdkcore/signer/hkdf.py
huaweicloudsdkcore/signer/signer.py
huaweicloudsdkcore/signer/utils.py
huaweicloudsdkcore/utils/__init__.py
huaweicloudsdkcore/utils/filepath_utils.py
huaweicloudsdkcore/utils/http_utils.py
huaweicloudsdkcore/utils/six_utils.py
huaweicloudsdkcore/utils/string_utils.py
huaweicloudsdkcore/utils/time_utils.py
huaweicloudsdkcore/utils/xml_utils.py
huaweicloudsdkcore/warning/__init__.py
huaweicloudsdkcore/warning/warning.py
huaweicloudsdkcore-3.1.184.dist-info/METADATA
huaweicloudsdkcore-3.1.184.dist-info/WHEEL
huaweicloudsdkcore-3.1.184.dist-info/licenses/LICENSE
huaweicloudsdkcore-3.1.184.dist-info/RECORD
