Metadata-Version: 2.4
Name: huaweicloudsdkcore
Version: 3.1.184
Summary: HuaweiCloud SDK Python Core
Project-URL: Homepage, https://github.com/huaweicloud/huaweicloud-sdk-python-v3
Author-email: HuaweiCloud SDK <hwcloudsdk@huawei.com>
License-Expression: Apache-2.0
License-File: LICENSE
Keywords: core,huaweicloud,sdk
Classifier: Development Status :: 5 - Production/Stable
Classifier: Intended Audience :: Developers
Classifier: License :: OSI Approved :: Apache Software License
Classifier: Programming Language :: Python :: 3.6
Classifier: Programming Language :: Python :: 3.7
Classifier: Programming Language :: Python :: 3.8
Classifier: Programming Language :: Python :: 3.9
Classifier: Programming Language :: Python :: 3.10
Classifier: Programming Language :: Python :: 3.11
Classifier: Programming Language :: Python :: 3.12
Classifier: Topic :: Software Development
Requires-Python: >=3.6
Requires-Dist: certifi>=2025.4.26
Requires-Dist: defusedxml
Requires-Dist: pyasn1>=0.5.0
Requires-Dist: pymongo
Requires-Dist: pyyaml>=6.0.1
Requires-Dist: requests-toolbelt>=0.10.1
Requires-Dist: simplejson>=3.20.2
Requires-Dist: six
Provides-Extra: test
Requires-Dist: pytest; extra == 'test'
Requires-Dist: pytest-cov; extra == 'test'
Requires-Dist: pytest-mock; extra == 'test'
Requires-Dist: requests-mock; extra == 'test'
Requires-Dist: responses; extra == 'test'
